daylily_carrier_tracking/__init__.py
daylily_carrier_tracking/cli.py
daylily_carrier_tracking/config.py
daylily_carrier_tracking/fedex_tracker.py
daylily_carrier_tracking/unified_tracker.py
daylily_carrier_tracking-0.1.0.dist-info/licenses/LICENSE
daylily_carrier_tracking-0.1.0.dist-info/METADATA
daylily_carrier_tracking-0.1.0.dist-info/WHEEL
daylily_carrier_tracking-0.1.0.dist-info/entry_points.txt
daylily_carrier_tracking-0.1.0.dist-info/top_level.txt
daylily_carrier_tracking-0.1.0.dist-info/RECORD
